umepr-0.0.1b37.dist-info/METADATA
umepr-0.0.1b37.dist-info/WHEEL
umepr-0.0.1b37.dist-info/licenses/LICENSE
umepr.libs/libgcc_s-98a1ef30.so.1
umepr/__init__.py
umepr/functions/daily_shading.py
umepr/functions/solweig.py
umepr/hybrid/svf.py
umepr/parametersforsolweig.json
umepr/rustalgos.cpython-39-x86_64-linux-gnu.so
umepr/shadows.py
umepr/solweig_runner_rust.py
umepr/svf.py
umepr-0.0.1b37.dist-info/RECORD
