Metadata-Version: 2.4
Name: umepr
Version: 0.0.1b37
Classifier: Programming Language :: Python :: 3.9
Classifier: Programming Language :: Python :: 3.10
Classifier: Programming Language :: Python :: 3.11
Classifier: Programming Language :: Python :: 3.12
Classifier: Programming Language :: Python :: 3.13
Requires-Dist: geopandas>=1.0.1
Requires-Dist: matplotlib>=3.9.4
Requires-Dist: momepy>=0.6.0
Requires-Dist: numpy>=2.0.2
Requires-Dist: pandas>=2.3.1
Requires-Dist: pvlib>=0.13.0
Requires-Dist: pyepw>=0.1
Requires-Dist: pyproj>=3.6.1
Requires-Dist: pytz>=2025.2
Requires-Dist: rasterio>=1.4.3
Requires-Dist: rioxarray>=0.15.0
Requires-Dist: scipy>=1.13.1
Requires-Dist: shapely>=2.0.7
Requires-Dist: tqdm>=4.67.1
Requires-Dist: umep>=0.0.1b47
Requires-Dist: xarray>=2024.7.0
License-File: LICENSE
Summary: rust implementation of urban multi-scale environmental predictor
Keywords: python3,geographical-information-system,spatial-data,spatial-data-analysis,urban-climate,urban-heat-island,urban-meteorology,urban-microclimate,urban-planning,urban-sustainability,urban-thermal-comfort,urban-thermal-environment,urban-thermal-mapping,urban-thermal-modelling,urban-thermal-simulation,urban-thermal-sustainability
Author: UMEP Developers
Maintainer: UMEP Developers
License: AGPL-3.0
Requires-Python: >=3.9, <3.14
Project-URL: homepage, https://github.com/UMEP-dev/umep-rust
Project-URL: documentation, https://github.com/UMEP-dev/umep-rust
Project-URL: repository, https://github.com/UMEP-dev/umep-rust
